damv1airtableprojectk8salert/__init__.py
damv1airtableprojectk8salert/myairtable_projectk8salert.py
damv1airtableprojectk8salert/myairtable_pywrapper.py
damv1airtableprojectk8salert/production_myairtable_projectk8salert.py
damv1airtableprojectk8salert/sandbox_myairtable_projectk8salert.py
damv1airtableprojectk8salert-0.5.15.dist-info/METADATA
damv1airtableprojectk8salert-0.5.15.dist-info/WHEEL
damv1airtableprojectk8salert-0.5.15.dist-info/top_level.txt
damv1airtableprojectk8salert-0.5.15.dist-info/RECORD
